openapi_jira_client/__init__.py
openapi_jira_client/api/__init__.py
openapi_jira_client/api/app_properties/__init__.py
openapi_jira_client/api/app_properties/addon_properties_resourcedelete_addon_property_delete.py
openapi_jira_client/api/app_properties/addon_properties_resourceget_addon_properties_get.py
openapi_jira_client/api/app_properties/addon_properties_resourceget_addon_property_get.py
openapi_jira_client/api/app_properties/addon_properties_resourceput_addon_property_put.py
openapi_jira_client/api/application_roles/__init__.py
openapi_jira_client/api/application_roles/get_all_application_roles.py
openapi_jira_client/api/application_roles/get_application_role.py
openapi_jira_client/api/audit_records/__init__.py
openapi_jira_client/api/audit_records/get_audit_records.py
openapi_jira_client/api/avatars/__init__.py
openapi_jira_client/api/avatars/delete_avatar.py
openapi_jira_client/api/avatars/get_all_system_avatars.py
openapi_jira_client/api/avatars/get_avatars.py
openapi_jira_client/api/avatars/store_avatar.py
openapi_jira_client/api/dashboards/__init__.py
openapi_jira_client/api/dashboards/copy_dashboard.py
openapi_jira_client/api/dashboards/create_dashboard.py
openapi_jira_client/api/dashboards/delete_dashboard.py
openapi_jira_client/api/dashboards/delete_dashboard_item_property.py
openapi_jira_client/api/dashboards/get_all_dashboards.py
openapi_jira_client/api/dashboards/get_dashboard.py
openapi_jira_client/api/dashboards/get_dashboard_item_property.py
openapi_jira_client/api/dashboards/get_dashboard_item_property_keys.py
openapi_jira_client/api/dashboards/get_dashboards_paginated.py
openapi_jira_client/api/dashboards/set_dashboard_item_property.py
openapi_jira_client/api/dashboards/update_dashboard.py
openapi_jira_client/api/dynamic_modules/__init__.py
openapi_jira_client/api/dynamic_modules/dynamic_modules_resourceget_modules_get.py
openapi_jira_client/api/dynamic_modules/dynamic_modules_resourceregister_modules_post.py
openapi_jira_client-3.0.1.dist-info/WHEEL
openapi_jira_client-3.0.1.dist-info/METADATA
openapi_jira_client-3.0.1.dist-info/RECORD
